_macals.cpython-312-darwin.so
macals/__init__.py
macals/__main__.py
macals-0.1.0.dist-info/licenses/LICENSE
macals-0.1.0.dist-info/METADATA
macals-0.1.0.dist-info/WHEEL
macals-0.1.0.dist-info/top_level.txt
macals-0.1.0.dist-info/RECORD
