Metadata-Version: 2.4
Name: macals
Version: 0.1.0
Summary: Access ambient light sensor on macOS
Author-email: Matt Martz <matt@sivel.net>
License-Expression: MIT
Classifier: Intended Audience :: Developers
Classifier: Natural Language :: English
Classifier: Operating System :: MacOS :: MacOS X
Classifier: Programming Language :: Python :: 3
Classifier: Programming Language :: Python :: 3.11
Classifier: Programming Language :: Python :: 3.12
Classifier: Programming Language :: Python :: 3.13
Classifier: Programming Language :: Python :: 3 :: Only
Requires-Python: >=3.11
License-File: LICENSE
Dynamic: license-file
